RosettaPy/__init__.py
RosettaPy/rosetta.py
RosettaPy/rosetta_finder.py
RosettaPy/analyser/__init__.py
RosettaPy/analyser/ddg.py
RosettaPy/analyser/reu.py
RosettaPy/app/__init__.py
RosettaPy/app/abc.py
RosettaPy/app/cart_ddg.py
RosettaPy/app/fastrelax.py
RosettaPy/app/mutate_relax.py
RosettaPy/app/pross.py
RosettaPy/app/rosettaligand.py
RosettaPy/app/supercharge.py
RosettaPy/app/deps/cart_ddg/flags/cart2.script
RosettaPy/app/deps/cart_ddg/flags/ddG.options
RosettaPy/app/deps/cart_ddg/flags/ddG_relax.flag
RosettaPy/app/deps/cart_ddg/flags/flags
RosettaPy/app/deps/fastrelax/flags/fastrelax.example.flag
RosettaPy/app/deps/mutate_relax/flags/cluster_scoring.flags
RosettaPy/app/deps/mutate_relax/xml/mutant_validation_temp.xml
RosettaPy/app/deps/pross/flags/flags_nodelay
RosettaPy/app/deps/pross/xmls/design_new.xml
RosettaPy/app/deps/pross/xmls/filterscan_parallel.xml
RosettaPy/app/deps/pross/xmls/refine.xml
RosettaPy/app/deps/rosettaligand/flags/rosetta_ligand.flags
RosettaPy/app/deps/rosettaligand/xmls/rosetta_ligand.xml
RosettaPy/app/utils/CA_constraints.py
RosettaPy/app/utils/__init__.py
RosettaPy/app/utils/smiles2param.py
RosettaPy/common/__init__.py
RosettaPy/common/mutation.py
RosettaPy/node/__init__.py
RosettaPy/node/dockerized.py
RosettaPy/node/mpi.py
RosettaPy/node/native.py
RosettaPy/node/utils.py
RosettaPy/node/wsl.py
RosettaPy/utils/__init__.py
RosettaPy/utils/escape.py
RosettaPy/utils/escape.pyi
RosettaPy/utils/repository.py
RosettaPy/utils/task.py
RosettaPy/utils/tools.py
rosettapy-0.2.15.dist-info/entry_points.txt
rosettapy-0.2.15.dist-info/licenses/LICENSE
rosettapy-0.2.15.dist-info/WHEEL
rosettapy-0.2.15.dist-info/METADATA
rosettapy-0.2.15.dist-info/RECORD
