Metadata-Version: 2.4
Name: RosettaPy
Version: 0.2.15
Summary: A Python utility for wrapping Rosetta command line tools.
Author-email: Yinying Yao <yaoyy.hi@gmail.com>
Requires-Python: >=3.8
Classifier: Development Status :: 6 - Mature
Classifier: Operating System :: POSIX :: Linux
Classifier: Operating System :: MacOS :: MacOS X
Classifier: Intended Audience :: Developers
Classifier: License :: OSI Approved :: MIT License
Classifier: Programming Language :: Python :: 3 :: Only
Classifier: Programming Language :: Python :: 3.8
Classifier: Programming Language :: Python :: 3.9
Classifier: Programming Language :: Python :: 3.10
Classifier: Programming Language :: Python :: 3.11
Classifier: Programming Language :: Python :: 3.12
Classifier: Programming Language :: Python :: 3.13
Classifier: Programming Language :: Python :: 3.14
License-File: LICENSE
Requires-Dist: joblib
Requires-Dist: absl-py
Requires-Dist: pandas
Requires-Dist: biopython
Requires-Dist: rdkit
Requires-Dist: numpy>=1.20.3,<3
Requires-Dist: matplotlib
Requires-Dist: docker>=7.1.0
Requires-Dist: gitpython
Requires-Dist: dm-tree
Requires-Dist: joblib-progress
Requires-Dist: pyspark>=3.0.0 ; extra == "spark"
Requires-Dist: bandit[toml]>=1.7.10 ; extra == "test"
Requires-Dist: black<=25.1.0 ; extra == "test"
Requires-Dist: check-manifest<=0.50 ; extra == "test"
Requires-Dist: flake8-bugbear==24.12.12 ; extra == "test"
Requires-Dist: flake8-docstrings ; extra == "test"
Requires-Dist: flake8-formatter_junit_xml ; extra == "test"
Requires-Dist: flake8 ; extra == "test"
Requires-Dist: flake8-pyproject ; extra == "test"
Requires-Dist: pylint==3.2.7 ; extra == "test"
Requires-Dist: pylint_junit ; extra == "test"
Requires-Dist: pytest-cov<=6.2.1 ; extra == "test"
Requires-Dist: pytest-mock<3.14.2 ; extra == "test"
Requires-Dist: pytest-runner ; extra == "test"
Requires-Dist: pytest<=8.4.1 ; extra == "test"
Requires-Dist: pytest-order ; extra == "test"
Requires-Dist: pytest-xdist>=3.6.1 ; extra == "test"
Requires-Dist: pytest-github-actions-annotate-failures ; extra == "test"
Requires-Dist: shellcheck-py>=0.10.0.1 ; extra == "test"
Requires-Dist: pre-commit ; extra == "test"
Requires-Dist: virtualenv<=20.33.1 ; extra == "test"
Project-URL: Documentation, https://github.com/YaoYinYing/RosettaPy/tree/main#readme
Project-URL: Source, https://github.com/YaoYinYing/RosettaPy
Project-URL: Tracker, https://github.com/YaoYinYing/RosettaPy/issues
Provides-Extra: spark
Provides-Extra: test
